odoo/addons/stock_inventory_include_exhausted/README.rst
odoo/addons/stock_inventory_include_exhausted/__init__.py
odoo/addons/stock_inventory_include_exhausted/__manifest__.py
odoo/addons/stock_inventory_include_exhausted/i18n/es.po
odoo/addons/stock_inventory_include_exhausted/i18n/stock_inventory_include_exhausted.pot
odoo/addons/stock_inventory_include_exhausted/models/__init__.py
odoo/addons/stock_inventory_include_exhausted/models/stock_inventory.py
odoo/addons/stock_inventory_include_exhausted/readme/CONTRIBUTORS.rst
odoo/addons/stock_inventory_include_exhausted/readme/DESCRIPTION.rst
odoo/addons/stock_inventory_include_exhausted/readme/USAGE.rst
odoo/addons/stock_inventory_include_exhausted/static/description/icon.png
odoo/addons/stock_inventory_include_exhausted/static/description/index.html
odoo/addons/stock_inventory_include_exhausted/tests/__init__.py
odoo/addons/stock_inventory_include_exhausted/tests/test_stock_inventory_include_exhausted.py
odoo/addons/stock_inventory_include_exhausted/views/stock_inventory_view.xml
odoo14_addon_stock_inventory_include_exhausted-14.0.1.0.1.dev2.dist-info/METADATA
odoo14_addon_stock_inventory_include_exhausted-14.0.1.0.1.dev2.dist-info/WHEEL
odoo14_addon_stock_inventory_include_exhausted-14.0.1.0.1.dev2.dist-info/top_level.txt
odoo14_addon_stock_inventory_include_exhausted-14.0.1.0.1.dev2.dist-info/RECORD
